{
  "version": "7",
  "dialect": "sqlite",
  "entries": [
    {
      "idx": 0,
      "version": "6",
      "when": 1725691747443,
      "tag": "0000_tan_tempest",
      "breakpoints": true
    },
    {
      "idx": 1,
      "version": "6",
      "when": 1725692582545,
      "tag": "0001_loving_monster_badoon",
      "breakpoints": true
    },
    {
      "idx": 2,
      "version": "6",
      "when": 1725758120987,
      "tag": "0002_grey_mephistopheles",
      "breakpoints": true
    },
    {
      "idx": 3,
      "version": "6",
      "when": 1726104425258,
      "tag": "0003_safe_ultimo",
      "breakpoints": true
    }
  ]
}